raindrop/__init__.py
raindrop/client.py
raindrop/transport.py
raindrop/types.py
raindrop/wrappers/__init__.py
raindrop/wrappers/anthropic.py
raindrop/wrappers/openai.py
rd_mini-0.1.0.dist-info/METADATA
rd_mini-0.1.0.dist-info/WHEEL
rd_mini-0.1.0.dist-info/RECORD
