Metadata-Version: 2.4
Name: rd-mini
Version: 0.1.0
Summary: Zero-config AI observability. Two lines to get started.
Project-URL: Repository, https://github.com/ryandonofrio/rd-mini
Author-email: RD <rd@example.com>
License: MIT
Keywords: ai,anthropic,llm,observability,openai,tracing
Classifier: Development Status :: 4 - Beta
Classifier: Intended Audience :: Developers
Classifier: License :: OSI Approved :: MIT License
Classifier: Programming Language :: Python :: 3
Classifier: Programming Language :: Python :: 3.9
Classifier: Programming Language :: Python :: 3.10
Classifier: Programming Language :: Python :: 3.11
Classifier: Programming Language :: Python :: 3.12
Classifier: Topic :: Software Development :: Libraries :: Python Modules
Requires-Python: >=3.9
Requires-Dist: httpx>=0.25.0
Provides-Extra: all
Requires-Dist: anthropic>=0.18.0; extra == 'all'
Requires-Dist: openai>=1.0.0; extra == 'all'
Provides-Extra: anthropic
Requires-Dist: anthropic>=0.18.0; extra == 'anthropic'
Provides-Extra: dev
Requires-Dist: anthropic>=0.18.0; extra == 'dev'
Requires-Dist: openai>=1.0.0; extra == 'dev'
Requires-Dist: pytest-asyncio>=0.21.0; extra == 'dev'
Requires-Dist: pytest>=7.0.0; extra == 'dev'
Provides-Extra: openai
Requires-Dist: openai>=1.0.0; extra == 'openai'
